wmul_file_manager/AnnualArchiver.py
wmul_file_manager/BulkCopier.py
wmul_file_manager/CompressMediaInFolder.py
wmul_file_manager/CopyYesterdaysSkimmerFiles.py
wmul_file_manager/CreateNewsFolders.py
wmul_file_manager/DeleteJunkFiles.py
wmul_file_manager/DeleteOldFiles.py
wmul_file_manager/DidTheSkimmerCopyTheFiles.py
wmul_file_manager/EquivalentFileFinder.py
wmul_file_manager/FindOldDirectories.py
wmul_file_manager/FolderComparer.py
wmul_file_manager/IsTheSkimmerWorking.py
wmul_file_manager/LongestPath.py
wmul_file_manager/__init__.py
wmul_file_manager/cli.py
wmul_file_manager/utilities/FileNamePrinter.py
wmul_file_manager/utilities/__init__.py
wmul_file_manager/utilities/directories.py
wmul_file_manager/utilities/ffmpeg.py
wmul_file_manager/utilities/graph.py
wmul_file_manager/utilities/skimmer_calendar.py
wmul_file_manager/utilities/writer.py
wmul_file_manager-1.1.0.dist-info/entry_points.txt
wmul_file_manager-1.1.0.dist-info/LICENSE
wmul_file_manager-1.1.0.dist-info/WHEEL
wmul_file_manager-1.1.0.dist-info/METADATA
wmul_file_manager-1.1.0.dist-info/RECORD
