Metadata-Version: 2.1
Name: wmul_file_manager
Version: 1.1.0
Summary: Various file management scripts for WMUL-FM.
Author-email: Michael Stanley <stanley50@marshall.edu>
Classifier: Programming Language :: Python :: 3
Classifier: License :: OSI Approved :: MIT License
Classifier: Operating System :: OS Independent
Classifier: Development Status :: 5 - Production/Stable
Requires-Dist: wmul_logger>=0.6.0
Requires-Dist: wmul_emailer>=0.6.0
Requires-Dist: click
Requires-Dist: networkx
Requires-Dist: tzdata
Requires-Dist: pydantic
Requires-Dist: pytest ; extra == "test"
Requires-Dist: pytest-mock ; extra == "test"
Requires-Dist: pyfakefs ; extra == "test"
Requires-Dist: wmul_test_utils>=0.4.0 ; extra == "test"
Requires-Dist: tox ; extra == "tox"
Project-URL: Bug Tracker, https://github.com/MikeTheHammer/wmul_file_manager/issues
Project-URL: Home, https://github.com/MikeTheHammer/wmul_file_manager
Provides-Extra: test
Provides-Extra: tox
